{
  "NVMe PCIe M.2 (Primary Storage)": [
    {
      "Name": "Samsung 980 Pro (1TB)",
      "Price (INR)": "17500",
      "urls": [
        "https://m.media-amazon.com/images/I/71bvF9MNa4S._AC_UF1000,1000_QL80_.jpg",
        "https://images.fonearena.com/blog/wp-content/uploads/2021/02/samsung-980Pro-SSD-fonearena_8.jpg"
      ]
    },
    {
      "Name": "WD Black SN850 (500GB)",
      "Price (INR)": "10500",
      "urls": [
        "https://example.com/wdblacksn850.jpg"
      ]
    },
    {
      "Name": "Crucial P5 Plus (1TB)",
      "Price (INR)": "12000",
      "urls": [
        "https://example.com/crucialp5plus.jpg"
      ]
    },
    {
      "Name": "Seagate FireCuda 530 (500GB)",
      "Price (INR)": "11500",
      "urls": [
        "https://example.com/seagatefirecuda530.jpg"
      ]
    },
    {
      "Name": "Gigabyte Aorus Gen4 7000 (1TB)",
      "Price (INR)": "13000",
      "urls": [
        "https://example.com/gigabyteaorusgen47000.jpg"
      ]
    },
    {
      "Name": "ADATA XPG Gammix S70 Blade (1TB)",
      "Price (INR)": "14500",
      "urls": [
        "https://example.com/adatagammixs70blade.jpg"
      ]
    },
    {
      "Name": "Kingston KC3000 (500GB)",
      "Price (INR)": "10800",
      "urls": [
        "https://example.com/kingstonkc3000.jpg"
      ]
    },
    {
      "Name": "Samsung 970 EVO Plus (500GB)",
      "Price (INR)": "7500",
      "urls": [
        "https://example.com/samsung970evoplus.jpg"
      ]
    },
    {
      "Name": "WD Blue SN570 (500GB)",
      "Price (INR)": "6800",
      "urls": [
        "https://example.com/wdbluesn570.jpg"
      ]
    },
    {
      "Name": "Crucial P2 (500GB)",
      "Price (INR)": "5500",
      "urls": [
        "https://example.com/crucialp2.jpg"
      ]
    }
  ],
  "SATA III SSD (Secondary Storage)": [
    {
      "Name": "Crucial BX500 (1TB)",
      "Price (INR)": "10000",
      "urls": [
        "https://5.imimg.com/data5/SELLER/Default/2022/10/ZV/JI/PM/120030640/61isgtwaiel-sl1280--500x500.jpg",
        "https://m.media-amazon.com/images/I/51zhuXxYuRL._AC_UF1000,1000_QL80_.jpg"
      ]
    },
    {
      "Name": "Samsung 870 QVO (1TB)",
      "Price (INR)": "7200",
      "urls": [
        "https://example.com/samsung870qvo.jpg"
      ]
    },
    {
      "Name": "WD Blue 3D NAND (500GB)",
      "Price (INR)": "3500",
      "urls": [
        "https://example.com/wdblue3dnand.jpg"
      ]
    },
    {
      "Name": "Kingston A400 (240GB)",
      "Price (INR)": "1800",
      "urls": [
        "https://example.com/kingstona400.jpg"
      ]
    },
    {
      "Name": "ADATA Ultimate SU650 (512GB)",
      "Price (INR)": "3200",
      "urls": [
        "https://example.com/adataultimateSU650.jpg"
      ]
    },
    {
      "Name": "Seagate BarraCuda (1TB)",
      "Price (INR)": "5800",
      "urls": [
        "https://example.com/seagatebarracuda.jpg"
      ]
    },
    {
      "Name": "Silicon Power A55 (480GB)",
      "Price (INR)": "3000",
      "urls": [
        "https://example.com/siliconpowerA55.jpg"
      ]
    },
    {
      "Name": "Team Group GX2 (250GB)",
      "Price (INR)": "1600",
      "urls": [
        "https://example.com/teamgroupGX2.jpg"
      ]
    },
    {
      "Name": "Transcend SSD370S (1TB)",
      "Price (INR)": "6500",
      "urls": [
        "https://example.com/transcendSSD370S.jpg"
      ]
    },
    {
      "Name": "Integral UD330 (480GB)",
      "Price (INR)": "2800",
      "urls": [
        "https://example.com/integralUD330.jpg"
      ]
    }
  ],
  "HDD (Secondary Storage)": [
    {
      "Name": "Seagate Barracuda (1TB)",
      "Price (INR)": "3200",
      "urls": [
        "https://www.seagate.com/content/dam/seagate/migrated-assets/www-content/products/hard-drives/barracuda-hard-drive/_shared/images/barracuda-3-5-1tb-hero-left-400x400.png",
        "https://computerspace.in/cdn/shop/products/NewProject-2021-06-19T134636.072.jpg?v=1629049832"
      ]
    },
    {
      "Name": "Western Digital Blue (2TB)",
      "Price (INR)": "4500",
      "urls": [
        "https://example.com/westerndigitalblueHDD.jpg"
      ]
    },
    {
      "Name": "Toshiba P300 (4TB)",
      "Price (INR)": "6800",
      "urls": [
        "https://example.com/toshibap300HDD.jpg"
      ]
    },
    {
      "Name": "HGST Deskstar NAS (4TB)",
      "Price (INR)": "7200",
      "urls": [
        "https://example.com/hgstdeskstarHDD.jpg"
      ]
    },
    {
      "Name": "WD Red Plus (4TB)",
      "Price (INR)": "7500",
      "urls": [
        "https://example.com/wdredplusHDD.jpg"
      ]
    },
    {
      "Name": "Seagate IronWolf (6TB)",
      "Price (INR)": "9000",
      "urls": [
        "https://example.com/seagateironwolfHDD.jpg"
      ]
    },
    {
      "Name": "Toshiba N300 NAS (4TB)",
      "Price (INR)": "7000",
      "urls": [
        "https://example.com/toshiban300HDD.jpg"
      ]
    },
    {
      "Name": "Western Digital Black (4TB)",
      "Price (INR)": "8200",
      "urls": [
        "https://example.com/westerndigitalblackHDD.jpg"
      ]
    },
    {
      "Name": "Seagate SkyHawk (4TB)",
      "Price (INR)": "7800",
      "urls": [
        "https://example.com/seagateskyhawkHDD.jpg"
      ]
    },
    {
      "Name": "Fujitsu Deskstar Eco (4TB)",
      "Price (INR)": "6200",
      "urls": [
        "https://example.com/fujitsudeskstarHDD.jpg"
      ]
    }
  ]
}
